{
  "hdtnConfigName": "node-b",
  "myNodeId": 2,
  "mySchemeStr": "ipn",
  "myDtnEidStr": "ipn:2.0",
  "storagePath": "/var/hdtn/storage-b",
  "inductsConfig": {
    "inductVector": [
      {
        "convergenceLayer": "ltp_over_udp",
        "name": "node-b-udp-induct",
        "boundPort": 4556,
        "thisLtpEngineId": 2,
        "remoteLtpEngineId": 1
      },
      {
        "convergenceLayer": "kiss",
        "name": "node-b-kiss-induct",
        "kissTncDevice": "/dev/ttyUSB1",
        "kissBaudRate": 9600,
        "thisLtpEngineId": 2,
        "remoteLtpEngineId": 1
      }
    ]
  },
  "outductsConfig": {
    "outductVector": [
      {
        "convergenceLayer": "ltp_over_udp",
        "name": "node-b-udp-outduct",
        "nextHopNodeId": 1,
        "remoteHostname": "192.168.1.1",
        "remotePort": 4556,
        "thisLtpEngineId": 2,
        "remoteLtpEngineId": 1
      },
      {
        "convergenceLayer": "kiss",
        "name": "node-b-kiss-outduct",
        "nextHopNodeId": 1,
        "kissTncDevice": "/dev/ttyUSB1",
        "kissBaudRate": 9600,
        "thisLtpEngineId": 2,
        "remoteLtpEngineId": 1
      }
    ]
  },
  "contactPlanJson": {
    "contacts": [
      {
        "source": 2,
        "dest": 1,
        "startTime": 0,
        "endTime": 86400,
        "rateBitsPerSec": 9600
      },
      {
        "source": 1,
        "dest": 2,
        "startTime": 0,
        "endTime": 86400,
        "rateBitsPerSec": 9600
      }
    ]
  }
}